bufferedthreadediterator.py
bufferedthreadediterator-2025.4.2.dist-info/LICENSE.md
bufferedthreadediterator-2025.4.2.dist-info/METADATA
bufferedthreadediterator-2025.4.2.dist-info/WHEEL
bufferedthreadediterator-2025.4.2.dist-info/top_level.txt
bufferedthreadediterator-2025.4.2.dist-info/RECORD
